Workbook

Sheet Orçamento
B2: Item | C2: Perfil / uso | D2: Qtd | E2: Preço unit. (R$) | F2: Subtotal (R$) | G2: Fornecedor | H2: URL da consulta | I2: Data da consulta | J2: Status do preço
B5: AMD Ryzen 5 8500G (100-100000931BOX) | C5: OPE – desktops | D5: 10 | E5: 799.99 | F5: =IF(E5="","",D5*E5) -> 7999.9 | G5: terabyteshop | H5: https://www.terabyteshop.com.br/produto/27321/processador-amd-ryzen-5-8500g-35ghz-50ghz-turbo-6-cores-12-threads-am5-com-cooler-amd-wraith-stealth-100-100001491box | I5: 46307 | J5: Confirmado
B6: AMD Ryzen 5 8600G (100-100001237BOX) | C6: ADM – desktops | D6: 11 | E6: 969.99 | F6: =IF(E6="","",D6*E6) -> 10669.89 | G6: terabyteshop | H6: https://www.terabyteshop.com.br/produto/27326/processador-amd-ryzen-5-8600g-43ghz-50ghz-turbo-6-cores-12-threads-am5-com-cooler-amd-wraith-stealth-100-100001237box | I6: 46301 | J6: Confirmado
B7: AMD Ryzen 7 8700G (100-100001236SBX) | C7: ESP – desktops | D7: 19 | E7: 1359.99 | F7: =IF(E7="","",D7*E7) -> 25839.81 | G7: terabyteshop | H7: https://www.terabyteshop.com.br/produto/39451/processador-amd-ryzen-7-8700g-42ghz-51ghz-turbo-8-cores-16-threads-am5-100-100001236sbx | I7: 46301 | J7: Confirmado
B8: ASRock B650M-HDV/M.2 (90-MXBLA0-A0UAYZ) | C8: Todos os desktops | D8: 40 | E8: 899.99 | F8: =IF(E8="","",D8*E8) -> 35999.6 | G8: terabyteshop | H8: https://www.terabyteshop.com.br/produto/27285/placa-mae-asrock-b650m-hdvm2-chipset-b650-amd-am5-m-atx-ddr5-90-mxbla0-a0uayz | I8: 46307 | J8: Confirmado
B9: Kingston FURY Beast 16 GB (2×8) DDR5-5600 (KF556C40BBK2-16) | C9: OPE e ADM | D9: 21 | E9: 2879.9 | F9: =IF(E9="","",D9*E9) -> 60477.9 | G9: terabyteshop | H9: https://www.terabyteshop.com.br/produto/23965/memoria-ddr5-kingston-fury-beast-16gb-2x8gb-5600mhz-black-kf556c40bbk2-16 | I9: 46301 | J9: Confirmado
B10: Kingston FURY Beast RGB 32 GB (2×16) DDR5-5600 CL36, branco (KF556C36BWEAK2-32) | C10: ESP | D10: 19 | E10: 4149.99 | F10: =IF(E10="","",D10*E10) -> 78849.81 | G10: kabum | H10: https://www.kabum.com.br/produto/448302/memoria-ram-kingston-fury-beast-rgb-32gb-2x16gb-5600mhz-ddr5-cl36-branco-kf556c36bweak2-32 | I10: 46301 | J10: Confirmado
B11: Kingston NV3 500 GB (SNV3S/500G) | C11: OPE e ADM | D11: 21 | E11: 699.99 | F11: =IF(E11="","",D11*E11) -> 14699.79 | G11: kabum | H11: https://www.kabum.com.br/produto/632571/ssd-500gb-m-2-nvme-pcie-4-5000mb-s-leit-3000mb-s-grav-nv3-snv3s-500g-kingston | I11: 46301 | J11: Confirmado
B12: Kingston NV3 1 TB (SNV3S/1000G) | C12: ESP | D12: 19 | E12: 1199.99 | F12: =IF(E12="","",D12*E12) -> 22799.81 | G12: kabum | H12: https://www.kabum.com.br/produto/621162/ssd-kingston-nv3-1-tb-m-2-2280-pcie-4-0-x4-nvme-leitura-6000-mb-s-gravacao-4000-mb-s-azul-snv3s-1000g | I12: 46301 | J12: Confirmado
B13: Fonte Corsair CX650 650 W 80 Plus Bronze (CP-9020278-BR) | C13: Todos os desktops | D13: 40 | E13: 379.99 | F13: =IF(E13="","",D13*E13) -> 15199.6 | G13: terabyteshop | H13: https://www.terabyteshop.com.br/produto/28116/fonte-corsair-cx650-650w-80-plus-bronze-pfc-ativo-atx-cp-9020278-br | I13: 46308 | J13: Confirmado
B14: Gabinete Cooler Master MasterBox Q300L | C14: Todos os desktops | D14: 40 | E14: 519.99 | F14: =IF(E14="","",D14*E14) -> 20799.6 | G14: kabum | H14: https://www.kabum.com.br/produto/903460/gabinete-gamer-cooler-master-masterbox-q300l-vidro-temperado-painel-modular-micro-atx-preto | I14: 46301 | J14: Confirmado
B15: Notebook Lenovo ThinkPad E14 Gen 7 (AMD Ryzen 5 220, 16 GB, SSD 512 GB) (21T10016BO) | C15: ADM – notebooks | D15: 9 | E15: 7586.1 | F15: =IF(E15="","",D15*E15) -> 68274.9 | G15: kabum | H15: https://www.kabum.com.br/produto/1004449/notebook-lenovo-thinkpad-e14-amd-g7-amd-ryzen-5-220-16gb-512gb-ssd-windows-11-pro-14-21t10016bo-preto | I15: 46307 | J15: Confirmado
B16: Notebook Lenovo ThinkPad E14 Gen 7 (AMD Ryzen 7 250, 32 GB, SSD 1 TB) (21T1000TBO) | C16: ESP – notebook (TI) | D16: 1 | E16: 10367.1 | F16: =IF(E16="","",D16*E16) -> 10367.1 | G16: kabum | H16: https://www.kabum.com.br/produto/1004442/notebook-lenovo-thinkpad-e14-amd-g7-amd-ryzen-7-250-32gb-1tb-ssd-windows-11-pro-14-21t1000tbo-preto | I16: 46301 | J16: Confirmado
... B28: Cabo Adaptador Conversor Displayport Para HDMI | C28: ESP – desktops (2º monitor) | D28: 19 | E28: 116.39 | F28: =IF(E28="","",D28*E28) -> 2211.41 | G28: kabum | H28: https://www.kabum.com.br/produto/689091/cabo-adaptador-conversor-displayport-para-hdmi | I28: 46307 | J28: Confirmado
B29: TOTAL (soma dos itens com preço informado) | F29: =SUM(F5:F28) -> 529745.56

Sheet Conferência
B2: Verificação | C2: Esperado | D2: Encontrado | E2: Resultado
B5: CPUs = desktops (10 + 11 + 19) | C5: =10+11+19 -> 40 | D5: =Orçamento!D5+Orçamento!D6+Orçamento!D7 -> 40 | E5: =IF(C5=D5,"OK","REVISAR") -> OK
B6: Placas-mãe = desktops | C6: 40 | D6: =Orçamento!D8 -> 40 | E6: =IF(C6=D6,"OK","REVISAR") -> OK
B7: Kits de memória = desktops (21 + 19) | C7: =21+19 -> 40 | D7: =Orçamento!D9+Orçamento!D10 -> 40 | E7: =IF(C7=D7,"OK","REVISAR") -> OK
B8: SSDs = desktops (21 + 19) | C8: =21+19 -> 40 | D8: =Orçamento!D11+Orçamento!D12 -> 40 | E8: =IF(C8=D8,"OK","REVISAR") -> OK
B9: Fontes = desktops | C9: 40 | D9: =Orçamento!D13 -> 40 | E9: =IF(C9=D9,"OK","REVISAR") -> OK
B10: Gabinetes = desktops | C10: 40 | D10: =Orçamento!D14 -> 40 | E10: =IF(C10=D10,"OK","REVISAR") -> OK
B11: Notebooks (9 + 1) | C11: =9+1 -> 10 | D11: =Orçamento!D15+Orçamento!D16 -> 10 | E11: =IF(C11=D11,"OK","REVISAR") -> OK
B12: Monitores (10 + 11 + 9 + 38 + 2) | C12: =10+11+9+38+2 -> 70 | D12: =Orçamento!D17 -> 70 | E12: =IF(C12=D12,"OK","REVISAR") -> OK
B13: Teclado + mouse = postos (40 + 10) | C13: =40+10 -> 50 | D13: =Orçamento!D18 -> 50 | E13: =IF(C13=D13,"OK","REVISAR") -> OK
B14: Headsets (10 OPE + 11 ADM) | C14: =10+11 -> 21 | D14: =Orçamento!D19 -> 21 | E14: =IF(C14=D14,"OK","REVISAR") -> OK
B15: Webcams (11 ADM-desktop) | C15: 11 | D15: =Orçamento!D20 -> 11 | E15: =IF(C15=D15,"OK","REVISAR") -> OK
B16: Desktops + notebooks = funcionários | C16: =40+10 -> 50 | D16: =(Orçamento!D8)+(Orçamento!D15)+(Orçamento!D16) -> 50 | E16: =IF(C16=D16,"OK","REVISAR") -> OK

Sheet Comparação
B2: Critério | C2: Opção A (escolhida) | D2: Opção B (descartada)
B5: PERFIL ESP (desktop) — 19 unidades | C5: AMD Ryzen 7 8700G + 32 GB DDR5 + vídeo integrado Radeon 780M | D5: Intel Core i7-14700 + cooler PCYES + placa MSI PRO B760M-P DDR5 + 32 GB + vídeo integrado UHD 770
B6: Desempenho | C6: 8 núcleos / 16 threads: suficiente para IDE, Git, Docker e algumas VMs | D6: 20 núcleos / 28 threads (anúncio da Terabyte): mais desempenho em multitarefa pesada
B7: Compatibilidade | C7: Usa a mesma placa-mãe AM5 dos outros perfis | D7: Exigiria outra placa (LGA1700) e outra plataforma só para o ESP; o processador não traz cooler
B8: Custo | C8: =Orçamento!E7+Orçamento!E8+Orçamento!E10+Orçamento!E12+Orçamento!E13+Orçamento!E14 -> 8509.94 | D8: =Orçamento!E10+Orçamento!E12+Orçamento!E13+Orçamento!E14+C27+C28 -> 9304.93
B9: Consumo | C9: TDP de 65 W | D9: Base de 65 W, mas até 219 W em turbo (ficha técnica): pede fonte e ventilação maiores
B10: Garantia | C10: Garantia de loja (36 meses em listagens consultadas do 8500G; conferir a do 8700G) | D10: 48 meses no anúncio do i7-14700 (Terabyte); placa MSI com 36 meses
B11: Manutenção | C11: Peças padronizadas entre os 3 perfis: um estoque de reposição só | D11: Duas plataformas para manter
B12: Expansão | C12: Soquete AM5 aceita troca de CPU no futuro | D12: LGA1700 é fim de ciclo: sem upgrade de CPU
B13: Decisão | C13: Opção A: custa cerca de R$ 8.509,94 por posto contra R$ 9.304,93 da B (9% a mais, já contando o cooler do combo). Atende a carga real do ESP sem excesso, usa a mesma placa dos outros perfis e preserva a possibilidade de upgrade. A opção B só se justificaria se o Desenvolvimento rodasse cargas muito mais pesadas. (Preços de 13/10/2026.)
B15: SERVIDOR PRINCIPAL | C15: Dell PowerEdge R360 (Xeon E-2436, 64 GB ECC, PERC H355, RAID 10, fonte redundante) | D15: Servidor montado com peças de desktop (Ryzen 7 8700G, 64 GB DDR5 sem ECC, 4 SSDs, RAID por software)
B16: Confiabilidade | C16: Memória ECC corrige erros; componentes de classe servidor | D16: Sem ECC: erro de memória pode corromper dados sem aviso
B17: Energia | C17: Duas fontes hot-swap redundantes | D17: Fonte única: se queimar, o servidor para
B18: Armazenamento | C18: Controladora RAID por hardware; 8 baias hot-plug (4 livres) | D18: RAID por software; troca de disco exige desligar
B19: Suporte e garantia | C19: Suporte do fabricante (nível a confirmar na cotação) | D19: Garantia de loja por peça, sem suporte integrado
B20: Custo | C20: =Orçamento!E22+Orçamento!E23*Orçamento!D23+Orçamento!E24*Orçamento!D24 -> 61995.96 | D20: =Orçamento!E7+Orçamento!E8+Orçamento!E24*Orçamento!D24+Orçamento!E13+Orçamento!E14+C29 -> 41059.91
B21: Expansão | C21: Até 128 GB de RAM e mais 4 baias de disco | D21: Limitada: a placa tem 2 slots de memória, então 64 GB já é o máximo (2 módulos de 32 GB)
B22: Manutenção | C22: Rack 1U padronizado, fácil de substituir | D22: Montagem própria: depende de quem montou
B23: Decisão | C23: Opção A, mesmo custando mais (R$ 61.995,96 contra R$ 41.059,91 da B, cerca de 51% a mais): o servidor concentra os 6 serviços usados pelos 50 funcionários, e uma falha pararia a empresa. ECC, fonte redundante e troca a quente reduzem esse risco. (Preços de 13/10/2026.)
B26: PREÇOS DA OPÇÃO B (lidos em 13/10/2026) | C26: Preço (R$, à vista no Pix) | D26: Fonte
B27: Intel Core i7-14700 + cooler PCYES Frost Pulse (combo da Terabyte; o processador não traz cooler) | C27: 2354.98 | D27: https://www.terabyteshop.com.br/produto/27110/processador-intel-core-i7-14700-34-ghz-54ghz-turbo-14-geracao-20-cores-28-threads-lga-1700-bx8071514700
B28: Placa-mãe MSI PRO B760M-P DDR5 (LGA1700, mATX) | C28: 699.99 | D28: https://www.terabyteshop.com.br/produto/31719/placa-mae-msi-pro-b760m-p-ddr5-chipset-b760-intel-lga-1700-matx-ddr5
B29: Kit Kingston FURY Beast EXPO 64 GB (2×32 GB) DDR5-6000 CL30, sem ECC (KF560C30BBEK2-64) | C29: 9899.99 | D29: https://www.kabum.com.br/produto/616570/memoria-ram-kingston-fury-beast-expo-64gb-2x32gb-6000mt-s-ddr5-dimm-cl30-preto-kf560c30bbek2-64

Sheet Fontes
B2: Item | C2: URL | D2: Data da consulta | E2: Observação
B5: Ryzen 5 8500G (loja: inclui cooler Wraith Stealth) | C5: https://www.terabyteshop.com.br/produto/27321/processador-amd-ryzen-5-8500g-35ghz-50ghz-turbo-6-cores-12-threads-am5-com-cooler-amd-wraith-stealth-100-100001491box | D5: 05/10/2026 | E5: Preço não lido na página
B6: Ryzen 5 8500G (ficha: 65 W, Radeon 740M, PCIe 4) | C6: https://galaxus.be/en/s1/product/amd-ryzen-5-8500g-am5-350-ghz-6-core-processors-42390587 | D6: 05/10/2026 | E6: Loja europeia: só ficha técnica
B7: Ryzen 5 8600G (especificações) | C7: https://galaxus.fr/en/s1/product/amd-ryzen-5-8600g-am5-430-ghz-6-core-processors-42390586 | D7: 01/10/2026 | E7: Loja europeia: só ficha técnica
B8: ASRock B650M-HDV/M.2 | C8: https://www.kabum.com.br/produto/525050/placa-mae-asrock-b650m-hdv-m-2-amd-b650-matx-ddr5-preto-90-mxbla- | D8: 01/10/2026 | E8: Preço não lido na página
B9: Dell PowerEdge R360 (análise) | C9: https://www.storagereview.com/review/dell-poweredge-r360-server-review | D9: 02/10/2026
B10: ASRock B650M-HDV/M.2 (página oficial) | C10: https://www.asrock.com/mb/AMD/B650M-HDVM.2/index.asp | D10: 13/10/2026 | E10: Suporta Ryzen 9000, 8000 e 7000; HDMI e DisplayPort; USB-C traseira; BIOS Flashback
B11: APC SURTA1500XL (ficha técnica: 1500 VA / 1050 W, dupla conversão) | C11: https://icecat.fr/amp/p/vendorName/mpn/desc-1112790.html | D11: 12/10/2026 | E11: Ficha de catálogo (Icecat)
B12: APC SURTA1500XL (autonomia: 22,2 min a 525 W, 8,6 min a 1050 W) | C12: https://ubbthreads.com/store/item/APC-Smart-UPS-RT-1500VA-1050W-Tower-Double-Conversion-Online-SURTA1500XL-Re-_354540225141.html | D12: 12/10/2026 | E12: Valores típicos do fabricante em loja de revenda
B13: Gabinete Cooler Master Q300L (ficha) | C13: https://www.kabum.com.br/produto/903460/gabinete-gamer-cooler-master-masterbox-q300l-vidro-temperado-painel-modular-micro-atx-preto | D13: 13/10/2026 | E13: Aceita Micro-ATX e Mini-ITX; fonte até 160 mm; cooler até 159 mm
B14: Corsair CX650 na Terabyte | C14: https://www.terabyteshop.com.br/produto/28116/fonte-corsair-cx650-650w-80-plus-bronze-pfc-ativo-atx-cp-9020278-br | D14: 13/10/2026 | E14: R$ 379,99 no Pix; 12 meses de garantia; 22 unidades em estoque
B15: Corsair CX650 na Kabum (comprimento de 125 mm; 98 unidades) | C15: https://www.kabum.com.br/produto/516056/fonte-corsair-cx-series-cx650-650w-80-plus-bronze-com-cabo-preto-cp-9020278-br | D15: 13/10/2026 | E15: Alternativa com estoque
B16: Memória ECC UDIMM 32 GB DDR5-4800 (Kabum) | C16: https://www.kabum.com.br/produto/1070303/memoria-32gb-ddr5-para-dell-t160-r260-t360-r360 | D16: 13/10/2026 | E16: Ficha: ECC UDIMM; fabricante variável; 12 meses de garantia
B17: MSI PRO B760M-P DDR5 (Terabyte) | C17: https://www.terabyteshop.com.br/produto/31719/placa-mae-msi-pro-b760m-p-ddr5-chipset-b760-intel-lga-1700-matx-ddr5 | D17: 13/10/2026 | E17: R$ 699,99 no Pix; 36 meses de garantia
B18: Intel Core i7-14700 + cooler PCYES (Terabyte) | C18: https://www.terabyteshop.com.br/produto/27110/processador-intel-core-i7-14700-34-ghz-54ghz-turbo-14-geracao-20-cores-28-threads-lga-1700-bx8071514700 | D18: 13/10/2026 | E18: R$ 2.354,98 no combo (Pix)
B19: Kingston FURY Beast EXPO 64 GB (Kabum) | C19: https://www.kabum.com.br/produto/616570/memoria-ram-kingston-fury-beast-expo-64gb-2x32gb-6000mt-s-ddr5-dimm-cl30-preto-kf560c30bbek2-64 | D19: 13/10/2026 | E19: R$ 9.899,99 no Pix
